{
  "Title": "交给帝王大人吧",
  "TextBlockList": [
    {
      "Name": "",
      "Text": "",
      "ChoiceDataList": [],
      "ColorTextInfoList": []
    },
    {
      "Name": "东海帝王",
      "Text": "啊，找到了！\u3000喂！！",
      "ChoiceDataList": [],
      "ColorTextInfoList": []
    },
    {
      "Name": "东海帝王",
      "Text": "你是之前，在选拔赛之后\n想要招揽我的训练员对不对？\u3000是这样的对吧！",
      "ChoiceDataList": [],
      "ColorTextInfoList": []
    },
    {
      "Name": "东海帝王",
      "Text": "那么，稍微测试一下，请跟我来！",
      "ChoiceDataList": [
        "测试！？突然是要做什么！？",
        "测试！？突然是要做什么！？"
      ],
      "ColorTextInfoList": []
    },
    {
      "Name": "东海帝王",
      "Text": "关于这个——，那天之后会长和我说了，\n『请好好思考，并选择值得信赖的训练员』。",
      "ChoiceDataList": [],
      "ColorTextInfoList": []
    },
    {
      "Name": "东海帝王",
      "Text": "既然如此，还是直接让你训练我一次要来的更快一些吧？\n所以今天的测试！\u3000就是让我见识一下你的训练员之力♪",
      "ChoiceDataList": [],
      "ColorTextInfoList": []
    },
    {
      "Name": "独白",
      "Text": "……于是，为东海帝王制定的为期一天的训练\n就这么开始了――",
      "ChoiceDataList": [],
      "ColorTextInfoList": []
    },
    {
      "Name": "东海帝王",
      "Text": "诶——，『单脚跳』？\u3000在赛道上放置小跨栏，\n只靠一只脚跳过去的训练吗……",
      "ChoiceDataList": [],
      "ColorTextInfoList": []
    },
    {
      "Name": "东海帝王",
      "Text": "感觉很有趣的样子！\u3000目标时间呢？",
      "ChoiceDataList": [],
      "ColorTextInfoList": []
    },
    {
      "Name": "独白",
      "Text": "给东海帝王看了目标时间。\n虽然将目标设定成了比一般马娘还要高的水准……",
      "ChoiceDataList": [],
      "ColorTextInfoList": []
    },
    {
      "Name": "东海帝王",
      "Text": "什么嘛，就这种程度？\n简单简单！\u3000我去去就回！",
      "ChoiceDataList": [],
      "ColorTextInfoList": []
    },
    {
      "Name": "独白",
      "Text": "就像是跳跃着奔跑一样，东海帝王\n毫不费力地就达成了比目标时间还要高一档次的成绩！",
      "ChoiceDataList": [],
      "ColorTextInfoList": []
    },
    {
      "Name": "东海帝王",
      "Text": "呼。……喂，就这种程度吗？\n我可是还能再继续呢！",
      "ChoiceDataList": [],
      "ColorTextInfoList": []
    },
    {
      "Name": "独白",
      "Text": "接下来又指示她进行了各种各样的训练，\n每一项东海帝王都达到了超出预期的成绩……！",
      "ChoiceDataList": [],
      "ColorTextInfoList": []
    },
    {
      "Name": "东海帝王",
      "Text": "――结束啦！！\n怎么样？\u3000我的记录是最厉害的吧？",
      "ChoiceDataList": [
        "真的很厉害……！"
      ],
      "ColorTextInfoList": []
    },
    {
      "Name": "东海帝王",
      "Text": "是吧——！！\u3000诶嘿嘿，\n再多称赞称赞下无敌的帝王大人也是可以的哦～！",
      "ChoiceDataList": [
        "『无敌的帝王大人』？"
      ],
      "ColorTextInfoList": []
    },
    {
      "Name": "东海帝王",
      "Text": "没错。我至今为止就没有输给过任何人。\n无论什么比赛都能胜利，一直被大家称赞到现在了！",
      "ChoiceDataList": [],
      "ColorTextInfoList": []
    },
    {
      "Name": "东海帝王",
      "Text": "被称赞的感觉真的很畅快呢，\n称赞我，也就是说大家都认可我『很厉害！』吧。",
      "ChoiceDataList": [],
      "ColorTextInfoList": []
    },
    {
      "Name": "东海帝王",
      "Text": "初次比赛的时候也是，拿到第一名的时候，\n所有人都在尽情地喊着『好厉害啊！』之类的话！",
      "ChoiceDataList": [],
      "ColorTextInfoList": []
    },
    {
      "Name": "东海帝王",
      "Text": "这样，真的真的很爽啊！",
      "ChoiceDataList": [],
      "ColorTextInfoList": []
    },
    {
      "Name": "东海帝王",
      "Text": "而且，参加闪耀系列赛的话\n一定会有越来越多的人对我说『简直太厉害了！』吧？",
      "ChoiceDataList": [
        "所以来到特雷森学园了啊"
      ],
      "ColorTextInfoList": []
    },
    {
      "Name": "东海帝王",
      "Text": "叮咚叮咚！！\n就是这样♪",
      "ChoiceDataList": [],
      "ColorTextInfoList": []
    },
    {
      "Name": "东海帝王",
      "Text": "呜～，好期待啊～～！！\u3000好像早点参加GⅠ赛事啊！！\n好想听人说我才是最厉害的马娘啊！",
      "ChoiceDataList": [],
      "ColorTextInfoList": []
    },
    {
      "Name": "独白",
      "Text": "一直嘀嘀咕咕的东海帝王，\n似乎完全没有考虑过自己会失败这种事。",
      "ChoiceDataList": [],
      "ColorTextInfoList": []
    },
    {
      "Name": "独白",
      "Text": "但是，她实际的实力我已经亲眼所见，\n有点担心她是否能够真的就这样一路胜利下去……",
      "ChoiceDataList": [],
      "ColorTextInfoList": []
    },
    {
      "Name": "东海帝王",
      "Text": "啊，现在还在测试中呢。\n你的训练表已经结束了吗？\u3000已经可以放松了？",
      "ChoiceDataList": [],
      "ColorTextInfoList": []
    },
    {
      "Name": "独白",
      "Text": "最后再一次，想要见证东海帝王的实力。\n这样的话――",
      "ChoiceDataList": [
        "最后来测一下2500m的时间吧"
      ],
      "ColorTextInfoList": []
    },
    {
      "Name": "东海帝王",
      "Text": "2500m？\u3000这不是我擅长的吗！\n是想在适性距离下确认实力吗？",
      "ChoiceDataList": [],
      "ColorTextInfoList": []
    },
    {
      "Name": "东海帝王",
      "Text": "OK！\n那么，我去去就回♪",
      "ChoiceDataList": [],
      "ColorTextInfoList": []
    },
    {
      "Name": "东海帝王",
      "Text": "哈，哈……哈——！\n时间，是多少？",
      "ChoiceDataList": [
        "2分34秒……好快……！"
      ],
      "ColorTextInfoList": []
    },
    {
      "Name": "东海帝王",
      "Text": "噢，刷新了自我记录！\n好耶♪",
      "ChoiceDataList": [],
      "ColorTextInfoList": []
    },
    {
      "Name": "鲁道夫象征",
      "Text": "――2500m啊。\nGⅠ比赛的话，就是『有马纪念』。",
      "ChoiceDataList": [],
      "ColorTextInfoList": []
    },
    {
      "Name": "东海帝王",
      "Text": "哇，会长！？",
      "ChoiceDataList": [],
      "ColorTextInfoList": []
    },
    {
      "Name": "东海帝王",
      "Text": "怎么了怎么了？\n是来看我的吗！？",
      "ChoiceDataList": [],
      "ColorTextInfoList": []
    },
    {
      "Name": "鲁道夫象征",
      "Text": "啊，的确如此。",
      "ChoiceDataList": [],
      "ColorTextInfoList": []
    },
    {
      "Name": "鲁道夫象征",
      "Text": "比起这个……嗯。训练员君，不好意思突然拜托你，\n能帮我测一下我的成绩吗？",
      "ChoiceDataList": [],
      "ColorTextInfoList": []
    },
    {
      "Name": "鲁道夫象征",
      "Text": "和帝王刚才的一样赛程，2500m。",
      "ChoiceDataList": [],
      "ColorTextInfoList": []
    },
    {
      "Name": "东海帝王",
      "Text": "诶，会长也要跑吗！？\n太好了！！\u3000一定没问题吧，训练员！？",
      "ChoiceDataList": [
        "知道了，我测一下"
      ],
      "ColorTextInfoList": []
    },
    {
      "Name": "鲁道夫象征",
      "Text": "感谢你。\n那么，来吧。",
      "ChoiceDataList": [],
      "ColorTextInfoList": []
    },
    {
      "Name": "鲁道夫象征",
      "Text": "呼……\n训练员君，时间是？",
      "ChoiceDataList": [
        "是，2分32秒……！"
      ],
      "ColorTextInfoList": []
    },
    {
      "Name": "东海帝王",
      "Text": "会长……比我还要快两秒……！",
      "ChoiceDataList": [],
      "ColorTextInfoList": []
    },
    {
      "Name": "鲁道夫象征",
      "Text": "是啊。\n……你输了，帝王。",
      "ChoiceDataList": [],
      "ColorTextInfoList": []
    },
    {
      "Name": "东海帝王",
      "Text": "嗯，我输啦！\u3000果然会长很厉害啊～！！\n不愧是，最强的赛马娘呢！！",
      "ChoiceDataList": [],
      "ColorTextInfoList": []
    },
    {
      "Name": "鲁道夫象征",
      "Text": "没有别的要说的？",
      "ChoiceDataList": [],
      "ColorTextInfoList": []
    },
    {
      "Name": "东海帝王",
      "Text": "呃，别的？",
      "ChoiceDataList": [],
      "ColorTextInfoList": []
    },
    {
      "Name": "鲁道夫象征",
      "Text": "是啊。……再和你说一次，帝王。\n你现在，难道不是输给我了吗？",
      "ChoiceDataList": [],
      "ColorTextInfoList": []
    },
    {
      "Name": "东海帝王",
      "Text": "诶，诶？\u3000那个，呜。\n所以，会长很厉害……诶？",
      "ChoiceDataList": [],
      "ColorTextInfoList": []
    },
    {
      "Name": "鲁道夫象征",
      "Text": "原来如此……\n没什么，很抱歉这么突然。",
      "ChoiceDataList": [],
      "ColorTextInfoList": []
    },
    {
      "Name": "鲁道夫象征",
      "Text": "帝王，训练结束了吗？\n比起原地休息，不如稍微去外面走走吧。",
      "ChoiceDataList": [],
      "ColorTextInfoList": []
    },
    {
      "Name": "东海帝王",
      "Text": "啊，嗯！\u3000就这样吧！\n训练员，待会见了！！",
      "ChoiceDataList": [],
      "ColorTextInfoList": []
    },
    {
      "Name": "鲁道夫象征",
      "Text": "那么……\n训练员君，虽然很突然，还请你告诉我。",
      "ChoiceDataList": [],
      "ColorTextInfoList": []
    },
    {
      "Name": "鲁道夫象征",
      "Text": "你对帝王刚才的表现，是怎么想的？",
      "ChoiceDataList": [],
      "ColorTextInfoList": []
    },
    {
      "Name": "独白",
      "Text": "虽然无言的魄力给了我些许压力，但现在再回头思考一下。",
      "ChoiceDataList": [],
      "ColorTextInfoList": []
    },
    {
      "Name": "独白",
      "Text": "拥有压倒性的魄力与野心，被憧憬的对象\n兼绝对的强者所承认，输了也不会不甘心，这样的话――",
      "ChoiceDataList": [
        "只是现在这样的话，太可惜了……"
      ],
      "ColorTextInfoList": []
    },
    {
      "Name": "鲁道夫象征",
      "Text": "……！\u3000原来如此，『可惜』吗。\n不愧是学园专属训练员，真是独具慧眼。",
      "ChoiceDataList": [],
      "ColorTextInfoList": []
    },
    {
      "Name": "鲁道夫象征",
      "Text": "就是这样。……现在的帝王，将自己的可能性降低了。\n作为以顶点为目标的赛马娘，实在是太不幸了。",
      "ChoiceDataList": [],
      "ColorTextInfoList": []
    },
    {
      "Name": "鲁道夫象征",
      "Text": "好……\n实际上，我想诚恳地拜托你一件事。",
      "ChoiceDataList": [],
      "ColorTextInfoList": []
    },
    {
      "Name": "鲁道夫象征",
      "Text": "最近，我原本打算要和帝王进行比赛――",
      "ChoiceDataList": [],
      "ColorTextInfoList": []
    }
  ]
}