{
  "Title": "反省会",
  "TextBlockList": [
    {
      "Name": "",
      "Text": "",
      "ChoiceDataList": [],
      "ColorTextInfoList": []
    },
    {
      "Name": "独白",
      "Text": "某天上课时——",
      "ChoiceDataList": [],
      "ColorTextInfoList": []
    },
    {
      "Name": "老师A",
      "Text": "――はーい、それじゃストレッチから！\r\nまずは2人組を作ってくださーい。",
      "ChoiceDataList": [],
      "ColorTextInfoList": []
    },
    {
      "Name": "成田大进",
      "Text": "（嘁。）",
      "ChoiceDataList": [],
      "ColorTextInfoList": []
    },
    {
      "Name": "同学们",
      "Text": "ねーねー、一緒にやろ！\r\nやろやろー！！",
      "ChoiceDataList": [],
      "ColorTextInfoList": []
    },
    {
      "Name": "成田大进",
      "Text": "（啊……）",
      "ChoiceDataList": [],
      "ColorTextInfoList": []
    },
    {
      "Name": "同学A",
      "Text": "あ……あのっ、タイシンさん！\r\nペア、まだ決まってないなら……一緒にやる？",
      "ChoiceDataList": [],
      "ColorTextInfoList": []
    },
    {
      "Name": "成田大进",
      "Text": "………………嗯。",
      "ChoiceDataList": [],
      "ColorTextInfoList": []
    },
    {
      "Name": "成田大进",
      "Text": "あー……ったく。\r\n『2人組作って』系のヤツ、本当最悪。",
      "ChoiceDataList": [],
      "ColorTextInfoList": []
    },
    {
      "Name": "成田大进",
      "Text": "……愛想よくとか、絶対無理だし。\r\n貧乏くじ引いたって思っただろうなー……。",
      "ChoiceDataList": [],
      "ColorTextInfoList": []
    },
    {
      "Name": "成田大进",
      "Text": "哈啊……",
      "ChoiceDataList": [],
      "ColorTextInfoList": []
    },
    {
      "Name": "独白",
      "Text": "その日のナリタタイシンは、あまり\r\nトレーニングに身が入らなかったようだ……。",
      "ChoiceDataList": [],
      "ColorTextInfoList": []
    }
  ]
}