{
  "Title": "天皇赏(秋)之后・BNW，狂奔",
  "TextBlockList": [
    {
      "Name": "",
      "Text": "",
      "ChoiceDataList": [],
      "ColorTextInfoList": []
    },
    {
      "Name": "成田大进",
      "Text": "哈……哈……哈……！！",
      "ChoiceDataList": [],
      "ColorTextInfoList": []
    },
    {
      "Name": "实况",
      "Text": "昨年の菊花賞以来となりました、BNW対決！\r\n制しましたのは――ナリタタイシン！！\nナリタタイシンですっ！！",
      "ChoiceDataList": [],
      "ColorTextInfoList": []
    },
    {
      "Name": "独白",
      "Text": "（唔哦哦哦哦哦哦！）",
      "ChoiceDataList": [],
      "ColorTextInfoList": []
    },
    {
      "Name": "成田大进",
      "Text": "（啊啊……一点也不难受。\n反而觉得……还不错。）",
      "ChoiceDataList": [],
      "ColorTextInfoList": []
    },
    {
      "Name": "成田大进",
      "Text": "（アタシはやっぱり、レースで勝ちたい。\r\n自分で自分を信じられるようになるまで、\n勝ち続けたい）",
      "ChoiceDataList": [],
      "ColorTextInfoList": []
    },
    {
      "Name": "成田大进",
      "Text": "（けどこの『勝ち』が、こんなに心地よくて、\r\n嬉しいのは――）",
      "ChoiceDataList": [],
      "ColorTextInfoList": []
    },
    {
      "Name": "胜利奖券",
      "Text": "ぐやじいいいいいっ……！！\r\n全力だったのに、超全力だったのに負けたぁ！",
      "ChoiceDataList": [],
      "ColorTextInfoList": []
    },
    {
      "Name": "胜利奖券",
      "Text": "でもっ……\r\nおめでとぉぉぉお、タイシィィィン！！",
      "ChoiceDataList": [],
      "ColorTextInfoList": []
    },
    {
      "Name": "琵琶晨光",
      "Text": "哎……真是的……",
      "ChoiceDataList": [],
      "ColorTextInfoList": []
    },
    {
      "Name": "琵琶晨光",
      "Text": "――强到令人膛目结舌啊，我们的劲敌。",
      "ChoiceDataList": [],
      "ColorTextInfoList": []
    },
    {
      "Name": "成田大进",
      "Text": "……得托你们的福。",
      "ChoiceDataList": [],
      "ColorTextInfoList": []
    },
    {
      "Name": "独白",
      "Text": "BNWの頂点に立った、ナリタタイシン。\r\n彼女を讃える歓声は、いつまでもいつまでも\n鳴りやまないのだった……。",
      "ChoiceDataList": [],
      "ColorTextInfoList": []
    },
    {
      "Name": "成田大进",
      "Text": "那来讨论下下一次比赛吧。",
      "ChoiceDataList": [
        "好！你准备跑哪个比赛！？",
        "うん、どれにする！？"
      ],
      "ColorTextInfoList": []
    },
    {
      "Name": "成田大进",
      "Text": "テンション高っ。\r\n相変わらずウザいなアンタは。いいけど。",
      "ChoiceDataList": [],
      "ColorTextInfoList": []
    },
    {
      "Name": "成田大进",
      "Text": "……ここまできたら、走りたいでしょ。\r\n年末のグランプリレース――",
      "ChoiceDataList": [
        "『有马纪念』啊……！",
        "『有馬記念』だね……！"
      ],
      "ColorTextInfoList": [
        "グランプリ"
      ]
    },
    {
      "Name": "成田大进",
      "Text": "どうせ、チケットとハヤヒデの2人も\r\n出てくるだろうしさ。",
      "ChoiceDataList": [],
      "ColorTextInfoList": []
    },
    {
      "Name": "成田大进",
      "Text": "……試したいんだ。\r\n試して、確かめたい。",
      "ChoiceDataList": [],
      "ColorTextInfoList": []
    },
    {
      "Name": "成田大进",
      "Text": "你所相信的，我的『强大』。",
      "ChoiceDataList": [
        "好，试试看吧！！"
      ],
      "ColorTextInfoList": []
    },
    {
      "Name": "独白",
      "Text": "次なる目標は、『有馬記念』に定められた！",
      "ChoiceDataList": [],
      "ColorTextInfoList": [
        "有马纪念"
      ]
    }
  ]
}