{
  "Title": "大阪杯にむけて",
  "TextBlockList": [
    {
      "Name": "",
      "Text": "",
      "ChoiceDataList": [],
      "ColorTextInfoList": []
    },
    {
      "Name": "独白",
      "Text": "ついに『大阪杯』の日がやってきた。\r\n友人のダイワスカーレットも出走することに、\nファインモーションは明るくはしゃいでいる。",
      "ChoiceDataList": [],
      "ColorTextInfoList": []
    },
    {
      "Name": "独白",
      "Text": "しかし、努めて明るくしているようだった。\r\nトレーナーはレースの間はすべて忘れて\n楽しく走ろう……と伝える。",
      "ChoiceDataList": [],
      "ColorTextInfoList": []
    },
    {
      "Name": "独白",
      "Text": "だがファインモーションは、\r\n自分の立場を忘れることができない。\n彼女はいつもの笑顔でレースへ向かう……。",
      "ChoiceDataList": [],
      "ColorTextInfoList": []
    }
  ]
}