{
  "Title": "不可思议的评价",
  "TextBlockList": [
    {
      "Name": "",
      "Text": "",
      "ChoiceDataList": [],
      "ColorTextInfoList": []
    },
    {
      "Name": "独白",
      "Text": "『ホープフルS』に向け準備を進めていた\r\nある日。突如トレーナー室を訪れた\nカレンチャンから『抗議』を受ける。",
      "ChoiceDataList": [],
      "ColorTextInfoList": [
        "真机伶"
      ]
    },
    {
      "Name": "独白",
      "Text": "聞かされたのは、アドマイヤベガの\r\nオーバーワークについてだった。\nどうやら独りで相当無理をしているらしい。",
      "ChoiceDataList": [],
      "ColorTextInfoList": []
    },
    {
      "Name": "独白",
      "Text": "少しでいいから息抜きをしてほしい。\r\nその一心で連れ出した先は、\nプラネタリウムだった。",
      "ChoiceDataList": [],
      "ColorTextInfoList": []
    },
    {
      "Name": "独白",
      "Text": "すると帰り道、アドマイヤベガは少しだけ、\r\n自身の抱える使命や想いについて\n打ち明けてくれた。",
      "ChoiceDataList": [],
      "ColorTextInfoList": []
    },
    {
      "Name": "独白",
      "Text": "独りで抱えていた荷物を、少しだけでも\r\n降ろすことができたのか――以降、\nオーバーワークは抑えられたのだった。",
      "ChoiceDataList": [],
      "ColorTextInfoList": []
    }
  ]
}