{
  "Title": "不可思议的评价",
  "TextBlockList": [
    {
      "Name": "",
      "Text": "",
      "ChoiceDataList": [],
      "ColorTextInfoList": []
    },
    {
      "Name": "真机伶",
      "Text": "我抗议～～～！",
      "ChoiceDataList": [
        "？！"
      ],
      "ColorTextInfoList": []
    },
    {
      "Name": "独白",
      "Text": "ちゃんとお上品だった入室前のノックが\n嘘のように、カレンチャン――",
      "ChoiceDataList": [],
      "ColorTextInfoList": [
        "真机伶"
      ]
    },
    {
      "Name": "独白",
      "Text": "与爱慕织姬一起住在栗东宿舍，\n时刻把『可爱』挂在嘴边的这位赛马娘，\n此刻却不顾形象地站在门口嚷嚷。",
      "ChoiceDataList": [
        "抗、抗议是说……？"
      ],
      "ColorTextInfoList": []
    },
    {
      "Name": "真机伶",
      "Text": "当时是抗议织姬同学训练日程的事！",
      "ChoiceDataList": [],
      "ColorTextInfoList": []
    },
    {
      "Name": "真机伶",
      "Text": "你看，\n织姬同学不一向是比较禁欲的人嘛？",
      "ChoiceDataList": [],
      "ColorTextInfoList": []
    },
    {
      "Name": "真机伶",
      "Text": "就算我约她一起吃饭或者出去玩，\n她也十有八九会拒绝我。",
      "ChoiceDataList": [],
      "ColorTextInfoList": []
    },
    {
      "Name": "真机伶",
      "Text": "问她去做什么的话，她就说是去自主训练……",
      "ChoiceDataList": [],
      "ColorTextInfoList": []
    },
    {
      "Name": "真机伶",
      "Text": "最近はちょっと行き過ぎですぅーっ！\n毎日毎日、カレンが起きる前に\nお部屋を出て、寝てから帰ってくるんですよ！",
      "ChoiceDataList": [],
      "ColorTextInfoList": [
        "カレン"
      ]
    },
    {
      "Name": "真机伶",
      "Text": "而且周末也不愿意休息一下！\n真是的~想和织姬同学一起看的视频，\n已经堆得像山一样多了！",
      "ChoiceDataList": [],
      "ColorTextInfoList": []
    },
    {
      "Name": "真机伶",
      "Text": "会变成这样，\n一定是因为训练员的要求太严格了吧~？！",
      "ChoiceDataList": [
        "……！！"
      ],
      "ColorTextInfoList": []
    },
    {
      "Name": "独白",
      "Text": "聞いて、青ざめる。『ホープフルS』に\r\n向けて、凄まじく高いモチベーションを\n持っているようだとは思っていたが――",
      "ChoiceDataList": [],
      "ColorTextInfoList": []
    },
    {
      "Name": "独白",
      "Text": "没想到，在加强了负荷的训练之外，\n她还用自主训练把自己逼到这种地步……！",
      "ChoiceDataList": [
        "（得马上阻止她……！）"
      ],
      "ColorTextInfoList": []
    },
    {
      "Name": "真机伶",
      "Text": "——啊，看这表情，\n果然织姬同学什么都没和您说过对吧？",
      "ChoiceDataList": [],
      "ColorTextInfoList": []
    },
    {
      "Name": "真机伶",
      "Text": "织姬同学呢，\n有时我觉得她有点禁欲过度啦~",
      "ChoiceDataList": [],
      "ColorTextInfoList": []
    },
    {
      "Name": "真机伶",
      "Text": "不过既然您已经知道这件事了，\n交给您就没问题了吧？",
      "ChoiceDataList": [],
      "ColorTextInfoList": []
    },
    {
      "Name": "真机伶",
      "Text": "毕竟训练员，您是织姬同学的\n『训练员』嘛♪",
      "ChoiceDataList": [
        "啊啊……！谢谢！",
        "うん……！ありがとう！"
      ],
      "ColorTextInfoList": []
    },
    {
      "Name": "独白",
      "Text": "总之，必须想办法让紧张过度的爱慕织姬放松。\n也许给她一些可以放松的时间比较好吧。",
      "ChoiceDataList": [
        "对于她而言，能够放松的事情……"
      ],
      "ColorTextInfoList": []
    },
    {
      "Name": "独白",
      "Text": "虽然她从未向我透露过自己的兴趣，\n但就从我与她相处时注意到的信息来思考的话，\n结论是——",
      "ChoiceDataList": [],
      "ColorTextInfoList": []
    },
    {
      "Name": "爱慕织姬",
      "Text": "天文馆？",
      "ChoiceDataList": [
        "对。最近有个天文馆刚刚改修完成哦。"
      ],
      "ColorTextInfoList": []
    },
    {
      "Name": "爱慕织姬",
      "Text": "……怎么突然说起这个来。",
      "ChoiceDataList": [],
      "ColorTextInfoList": []
    },
    {
      "Name": "独白",
      "Text": "是从真机伶那儿听说的……\n我暂且决定把这件事情按下不表。斟词酌句后，\n我小心翼翼地告诉她，我最近觉得她有些过劳。",
      "ChoiceDataList": [
        "为了能继续参加比赛，休息也很重要哦。"
      ],
      "ColorTextInfoList": []
    },
    {
      "Name": "爱慕织姬",
      "Text": "这可不是说这种事情的时——",
      "ChoiceDataList": [
        "你就说去还是不去吧！",
        "興味がないか、見るだけ見てみない？"
      ],
      "ColorTextInfoList": []
    },
    {
      "Name": "独白",
      "Text": "そう言って、メッセージアプリ『LANE』にて\r\nアドマイヤベガに見つけたプラネタリウムの\nHPリンクを送信する。",
      "ChoiceDataList": [],
      "ColorTextInfoList": [
        "LANE"
      ]
    },
    {
      "Name": "爱慕织姬",
      "Text": "………………",
      "ChoiceDataList": [],
      "ColorTextInfoList": []
    },
    {
      "Name": "独白",
      "Text": "与叹着气拿出手机的爱慕织姬一起，\n我也再次阅读起这份介绍。",
      "ChoiceDataList": [],
      "ColorTextInfoList": []
    },
    {
      "Name": "独白",
      "Text": "那个天文馆在改修后装备了最新锐的投影仪，\n还配有号称是『就像躺在云朵上一般舒适』的\n靠垫椅——",
      "ChoiceDataList": [
        "机会难得，就选有靠垫椅的座位吧。"
      ],
      "ColorTextInfoList": []
    },
    {
      "Name": "爱慕织姬",
      "Text": "………………",
      "ChoiceDataList": [],
      "ColorTextInfoList": []
    },
    {
      "Name": "爱慕织姬",
      "Text": "……你已经买了票了吗？",
      "ChoiceDataList": [
        "因为现在人气太旺了，所以我先等一等……"
      ],
      "ColorTextInfoList": []
    },
    {
      "Name": "独白",
      "Text": "実際、現時点で既にチケットは予約可能分\r\n全て売り切れているほどの人気ぶりである。",
      "ChoiceDataList": [],
      "ColorTextInfoList": []
    },
    {
      "Name": "独白",
      "Text": "虽说如此，但其实票的事情可以先放一放，\n先决定到底去不去。\n我这样告诉她之后——",
      "ChoiceDataList": [],
      "ColorTextInfoList": []
    },
    {
      "Name": "爱慕织姬",
      "Text": "………………………………",
      "ChoiceDataList": [],
      "ColorTextInfoList": []
    },
    {
      "Name": "爱慕织姬",
      "Text": "……要是说，早去早回……",
      "ChoiceDataList": [],
      "ColorTextInfoList": []
    },
    {
      "Name": "爱慕织姬",
      "Text": "不占用训练的时间的话……",
      "ChoiceDataList": [],
      "ColorTextInfoList": []
    },
    {
      "Name": "爱慕织姬",
      "Text": "…………倒是可以去。",
      "ChoiceDataList": [],
      "ColorTextInfoList": []
    },
    {
      "Name": "独白",
      "Text": "总之，费劲九牛二虎之力，\n总算是把织姬带出来放松了……！",
      "ChoiceDataList": [],
      "ColorTextInfoList": []
    },
    {
      "Name": "爱慕织姬",
      "Text": "这就是……靠垫椅……",
      "ChoiceDataList": [
        "看上去可以躺下来看星星的样子。",
        "寝転がって見られるみたいだね"
      ],
      "ColorTextInfoList": []
    },
    {
      "Name": "爱慕织姬",
      "Text": "嗯，好像是呢。",
      "ChoiceDataList": [],
      "ColorTextInfoList": []
    },
    {
      "Name": "爱慕织姬",
      "Text": "天鹅绒的质感……",
      "ChoiceDataList": [],
      "ColorTextInfoList": []
    },
    {
      "Name": "爱慕织姬",
      "Text": "里面装的是……\n啊、果然……是塑料微珠……",
      "ChoiceDataList": [],
      "ColorTextInfoList": []
    },
    {
      "Name": "爱慕织姬",
      "Text": "……软绵绵的……",
      "ChoiceDataList": [],
      "ColorTextInfoList": []
    },
    {
      "Name": "爱慕织姬",
      "Text": "（真的……软绵绵的……）",
      "ChoiceDataList": [],
      "ColorTextInfoList": []
    },
    {
      "Name": "爱慕织姬",
      "Text": "…………………………",
      "ChoiceDataList": [],
      "ColorTextInfoList": []
    },
    {
      "Name": "独白",
      "Text": "——在返程的电车上。",
      "ChoiceDataList": [],
      "ColorTextInfoList": []
    },
    {
      "Name": "爱慕织姬",
      "Text": "…………你睡着了吗？",
      "ChoiceDataList": [
        "？"
      ],
      "ColorTextInfoList": []
    },
    {
      "Name": "爱慕织姬",
      "Text": "睡着了吗？",
      "ChoiceDataList": [],
      "ColorTextInfoList": []
    },
    {
      "Name": "独白",
      "Text": "这问题实在太过唐突，我不知如何是好——\n但织姬没有注意到我的惊慌失措，\n看也没看我这边，只是再度开口询问。",
      "ChoiceDataList": [],
      "ColorTextInfoList": []
    },
    {
      "Name": "独白",
      "Text": "那么――\n也许应该贯彻『沉默是金』原则。\n这么想着，我一言不发地紧闭双眼。",
      "ChoiceDataList": [
        "…………"
      ],
      "ColorTextInfoList": []
    },
    {
      "Name": "爱慕织姬",
      "Text": "……睡着了就好。\n……稍微听我说几句吧。",
      "ChoiceDataList": [],
      "ColorTextInfoList": []
    },
    {
      "Name": "爱慕织姬",
      "Text": "……您……训练员……\n真的，是一位令人费解的人呢。",
      "ChoiceDataList": [],
      "ColorTextInfoList": []
    },
    {
      "Name": "爱慕织姬",
      "Text": "我从来没对您说过任何我的事情。\n而您明明也不该知道这些事情——",
      "ChoiceDataList": [],
      "ColorTextInfoList": []
    },
    {
      "Name": "爱慕织姬",
      "Text": "…………………………",
      "ChoiceDataList": [],
      "ColorTextInfoList": []
    },
    {
      "Name": "爱慕织姬",
      "Text": "……在我的灵魂里，\n似乎残留着某种类似于残影的东西。",
      "ChoiceDataList": [],
      "ColorTextInfoList": []
    },
    {
      "Name": "爱慕织姬",
      "Text": "大概是……我以前和您提到过的，我的妹妹。\n那位替我身死的妹妹的残影。",
      "ChoiceDataList": [],
      "ColorTextInfoList": []
    },
    {
      "Name": "爱慕织姬",
      "Text": "我在比赛中奔跑时会心跳加速也是。\n在比赛中胜利时会喜不自胜也是。\n我想……那都是我妹妹的感情。",
      "ChoiceDataList": [],
      "ColorTextInfoList": []
    },
    {
      "Name": "爱慕织姬",
      "Text": "大概……她也喜欢吧。\n她一定是喜欢奔跑在赛场上的。",
      "ChoiceDataList": [],
      "ColorTextInfoList": []
    },
    {
      "Name": "爱慕织姬",
      "Text": "所以，我——",
      "ChoiceDataList": [],
      "ColorTextInfoList": []
    },
    {
      "Name": "爱慕织姬",
      "Text": "必须要带着妹妹的份，奔跑、取胜……\n为了明明想要奔跑，却无法奔跑的她……",
      "ChoiceDataList": [],
      "ColorTextInfoList": []
    },
    {
      "Name": "爱慕织姬",
      "Text": "即便留在我心中的，仅仅是她的些许残影……\n我也要为她献上她所追求的一切。",
      "ChoiceDataList": [],
      "ColorTextInfoList": []
    },
    {
      "Name": "爱慕织姬",
      "Text": "…………",
      "ChoiceDataList": [],
      "ColorTextInfoList": []
    },
    {
      "Name": "爱慕织姬",
      "Text": "……这件事，实际上和您没有任何关系。\n这也是您无需背负的事情。",
      "ChoiceDataList": [
        "（没有那种事情哦……）"
      ],
      "ColorTextInfoList": []
    },
    {
      "Name": "爱慕织姬",
      "Text": "……所以。\n您只在睡着后听我说说这件事……\n就足够了。",
      "ChoiceDataList": [],
      "ColorTextInfoList": []
    },
    {
      "Name": "爱慕织姬",
      "Text": "明天的训练——\n也拜托您了。",
      "ChoiceDataList": [],
      "ColorTextInfoList": []
    },
    {
      "Name": "独白",
      "Text": "她不再言语，而我也没有睁开眼。\n电车在寂静之中轻摇着，驶向星空下的月夜。",
      "ChoiceDataList": [],
      "ColorTextInfoList": []
    },
    {
      "Name": "独白",
      "Text": "等到她轻唤『该起来了』的时候，\n我们已经到了学园附近的车站。",
      "ChoiceDataList": [],
      "ColorTextInfoList": []
    },
    {
      "Name": "织姬的妹妹",
      "Text": "――――",
      "ChoiceDataList": [],
      "ColorTextInfoList": []
    },
    {
      "Name": "织姬的妹妹",
      "Text": "——训练……员。",
      "ChoiceDataList": [],
      "ColorTextInfoList": []
    },
    {
      "Name": "织姬的妹妹",
      "Text": "这个人就是……姐姐的——",
      "ChoiceDataList": [],
      "ColorTextInfoList": []
    },
    {
      "Name": "真机伶",
      "Text": "嗯~天气真不错呢~……",
      "ChoiceDataList": [],
      "ColorTextInfoList": []
    },
    {
      "Name": "真机伶",
      "Text": "欸、啊！织姬同学！\n你还没走吗？",
      "ChoiceDataList": [],
      "ColorTextInfoList": []
    },
    {
      "Name": "爱慕织姬",
      "Text": "……早上好。\n不希望我在吗？",
      "ChoiceDataList": [],
      "ColorTextInfoList": []
    },
    {
      "Name": "真机伶",
      "Text": "才没有不希望你在哦！不过不过、\n你最近早上天天跑去晨练！平时根本见不到你！",
      "ChoiceDataList": [],
      "ColorTextInfoList": []
    },
    {
      "Name": "真机伶",
      "Text": "而且、制服……\n就是说，你今天打算直接去上学吗？",
      "ChoiceDataList": [],
      "ColorTextInfoList": []
    },
    {
      "Name": "爱慕织姬",
      "Text": "……算是吧。",
      "ChoiceDataList": [],
      "ColorTextInfoList": []
    },
    {
      "Name": "爱慕织姬",
      "Text": "又来了……这种意义不明的关心……\n真令人费解……",
      "ChoiceDataList": [],
      "ColorTextInfoList": []
    },
    {
      "Name": "真机伶",
      "Text": "哈啊，那我们一起去学校吧♪\n稍等一会，我现在就去准备哦！",
      "ChoiceDataList": [],
      "ColorTextInfoList": []
    },
    {
      "Name": "爱慕织姬",
      "Text": "不等。",
      "ChoiceDataList": [],
      "ColorTextInfoList": []
    },
    {
      "Name": "真机伶",
      "Text": "不要啦不要啦！\n你要是不等我的话，我就堵住门不让你出去了哦！",
      "ChoiceDataList": [],
      "ColorTextInfoList": []
    },
    {
      "Name": "爱慕织姬",
      "Text": "……别闹了……\n万一有人想进来的话怎么办啊。",
      "ChoiceDataList": [],
      "ColorTextInfoList": []
    },
    {
      "Name": "爱慕织姬",
      "Text": "……五分钟。\n我就等你五分钟。",
      "ChoiceDataList": [],
      "ColorTextInfoList": []
    },
    {
      "Name": "真机伶",
      "Text": "好的～♪",
      "ChoiceDataList": [],
      "ColorTextInfoList": []
    }
  ]
}