{
    "13610741170754986310": "レース中間からロングスパートをかけて\n速度がわずかに上がる",
    "10531901581397172235": "残り200mを切って前の方にいると\n競り合いに強くなり速度が少し上がる",
    "4662562160813441432": "レース後半で1番を\nキープし続ける力をわずかに発揮する",
    "3431138585953240748": "最終直線で後ろの方から追い抜くと\n末脚を使って速度が少し上がる",
    "12644793748541312862": "最終直線で余力を持って前にいると\nわずかに優位を保ちやすくなる",
    "1464516257666838661": "最終コーナーで後ろから追い抜くと\n女帝たる走りで速度が少し上がる",
    "17877905842518098238": "最終コーナーで前の方で競り合うと\n直線でわずかに抜け出しやすくなる",
    "5591076290339878529": "レース終盤のコーナーで前の位置に\nつこうとして加速力が少し上がる",
    "7022188077473132417": "レース後半のコーナーで控えていると\n持久力が少し回復する",
    "15981166978657091224": "最終直線で競り合いに負けない\n気持ちが湧き、速度が少し上がる",
    "7404029575929275508": "レース後半に前の方で競り合うとバク\nシン力（？）を発揮、速度が少し上がる",
    "3332691736849368752": "レース中盤で好位置にいる時に\n持久力が少し回復する",
    "2251501612593573378": "最終コーナーで後ろの方にいると近くの\nウマ娘を見て持久力を少し回復する",
    "15773784779632447433": "レース終盤に前方が詰まると\nお告げの力で少し道を切り開く",
    "9507004544667343476": "レース終盤で3番手の時に負けそうに\nなると闘志に火が付き速度が少し上がる",
    "12384980096312629617": "レースを冷静に運ぶことができると\n残り200mで実力発揮、速度が上がる",
    "10287211098660717461": "レース終盤に前の方で相手を抜くと\n勢いに乗って速度が上がる",
    "13242469267027225607": "最終直線で差を付けて先頭にいると\nさらなる脚を使って、速度を上げる",
    "16661269178431323094": "最終直線で前と差が詰まると\n華麗な脚取りで速度がすごく上がる",
    "6771736003735807463": "最終コーナー以降で前の方にいると\nギアを変えて加速力が上がる",
    "9281674116132498471": "最終直線で前の方で少し抜け出ていると\n輝きを増し速度がすごく上がる",
    "11594560540923367995": "残り200m地点で前の方にいると\n道を開いてすごく抜け出しやすくなる",
    "1352736127160948795": "レース中間からロングスパートをかけて\n速度が少しずつ上がる",
    "16478964390366833649": "残り200mを切って前の方にいると\n競り合いに強くなり速度が上がる",
    "6513698728884340069": "レース後半で\n1番をキープし続ける力を発揮する",
    "12608367351508324368": "最終コーナーで好位置にいると\n弾みを付けて加速力が上がる",
    "7879856085749437158": "最終直線で後ろの方から追い抜くと\n末脚を使って速度が上がる",
    "4717566514968766367": "最終直線で後ろの方から外を回って\n追い抜く時、速度を上げる",
    "637049291845072587": "最終コーナーで前の方にいると\n抜かせない覚悟を決めて速度が上がる",
    "9662859439184657609": "最終直線で余力を持って前にいると\nより優位を保ちやすくなる",
    "940023375625708513": "最終コーナーで前の方で競り合うと\n王たる輝きで速度が上がる",
    "2140084251842786757": "最終コーナー以降で外から追い抜くと\n怪物的な力で、速度を上げる",
    "15030610556261413850": "レース終盤に3回追い抜くと\n最終直線で速度がすごく上がる",
    "18201604042979874175": "最終コーナーで後ろから追い抜くと\n女帝たる走りで速度が上がる",
    "6958413552795815054": "レース終盤に2回追い抜くと間近で拝む\nウマ娘ちゃんのあまりの尊さに思わず\n速度を上げる",
    "13503375946269693497": "レース終盤のコーナーで先頭にいると\nこれ幸いと加速力を上げる",
    "4664372343220843406": "レース後半の直線で好位置にいる\nまたは中団から前を狙うと\n稲妻の如く駆けて行く",
    "12111509388798453248": "レース後半に好位置で競り合うと\n走ることに心を躍らせて\n速度を上げる",
    "14851329549623153075": "最終コーナーで前の方で追い抜くと\n勝利の方程式を導き、速度を上げる",
    "14413225434400350403": "最終コーナーで前の方で競り合うと\n直線で抜け出しやすくなる",
    "3735349084427696204": "レース後半に中団から\n『お友達』を追って速度を少しずつ上げ\n前方のウマ娘をちょっと委縮させる",
    "4757432859312433150": "最終直線までみずから崩れることなく\n前の方にいると速度が上がる",
    "10987682121974392139": "レース終盤のコーナーで前の位置に\nつこうとして加速力が上がる",
    "13595656505659687835": "レース中間に好位置で少し疲れてくると\n気合を入れ直して大きく前へ踏み込む",
    "9666704973910942413": "最終直線で抜け出した時に\n強い意志を持って速度が上がる",
    "7942547695544284527": "レース後半のコーナーで控えていると\n持久力が回復する",
    "14043841428132767638": "最終直線で先頭から離されていると\n星に導かれるように速度が上がる\n最後方付近にいる場合はすごく上がる",
    "10004583361853563300": "最終直線で競り合いに負けない\n強い気持ちが湧き、速度が上がる",
    "13825351943926349375": "最終直線まで冷静に自身の計画通り\n走行出来れば、先頭目がけて鋭い脚で\n速度を上げる",
    "6645463328258293928": "レース中間付近で好位置にいる時に\n追い抜くと勢いづき進出を開始する",
    "7890295321706235081": "最終直線を走行中に中団で競り合うと\n可憐にぶっ飛ばして速度を上げる",
    "7984436585677120755": "レース後半に中団から仕掛け始める時に\n持てるパフォーマンスを発揮して\n加速力を少しずつ上げる",
    "11807342547932790518": "レース後半に前の方で競り合うと\nバクシン力（？）を発揮、速度が上がる",
    "11324941791224376942": "レース中盤で好位置にいる時に\n持久力が回復する",
    "13045537353725861850": "レース中盤の直線で先頭を奪われそうに\nなると譲らない想いが力になる",
    "16244440231297439178": "最終直線を走行中に好位置で\n追い抜くまたは詰め寄られると\nテンションを上げて速度を上げる",
    "2150168604030247508": "最終コーナーで集団の後方の位置から\n前へ出る時、切れ味が増し速度が上がる",
    "10642389382231321796": "最終コーナーで後ろの方にいると近くの\nウマ娘を見て持久力を回復する",
    "9499364873582833479": "レース終盤に前方が詰まると\nお告げの力で道を切り開く",
    "16646825200017060119": "レース終盤のコーナーで\n中団以降のポジションから追い抜くと\nあきらめない心を発揮して前を目指す",
    "9241230315997233935": "落ち着いたまま、中盤の仕掛けどころの\nまたは終盤の勝負どころのコーナーを\n中団で進むと奮い立ち加速力が上がる",
    "14875598909589859811": "レース終盤で3番手の時に負けそうにな\nると秘めた闘志に火が付き速度が上がる",
    "7701487907369375503": "レースを冷静に運ぶことができると残り\n200mで実力発揮、速度がすごく上がる",
    "10411109919089256489": "残り300mを切って好位置にいるとき\n前のウマ娘との距離が近いと\n強い想いが花開き速度が上がる",
    "7385491467041653471": "最終直線で後ろのウマ娘と距離が近いと\nこの瞬間に懸け持久力をわずかに使い\n少しの間速度がすごく上がる",
    "16854156781904352435": "中盤で2回スキルを使うと\nよりリラックスして持久力が回復する",
    "795180906197647755": "最終直線で前の方で追いすがっていると\n不屈の闘志で速度が上がる",
    "13405949976158017838": "スキルで持久力を回復すると\nレース後半で前のほうにいる時に\nレッツラゴー！と速度を上げる",
    "3127094278908849657": "スキルで持久力を3回以上回復すると\nレース後半で勝利に向かい\n呼吸を整えて力強く踏み込んでいく",
    "14674702207224715596": "中盤に後ろの方で順位を下げた時に\n優しい光で持久力を回復する",
    "5886764862762776563": "最終コーナー以降に前めで力が尽きかけ\n詰め寄られると速度が上がる",
    "11368137557282980775": "最終コーナーで中団から前を狙う時\n魂を燃え滾らせて加速力を上げる",
    "18228216687826731877": "残り400m地点で先団だと少しの間\n速度を上げる、それまでに7回スキルを\n使っている場合はすごく上げる",
    "613641285556654580": "最終コーナー以降に先団で\n詰め寄られると闘志を燃やして\n速度を上げる",
    "2231235035303991348": "レース中盤で前の方から\n仕掛け始める時に速度が上がる",
    "6573049926948037207": "スタート後からレース後半まで\n好位置を維持し続けるとレース中盤に\n勝利への道筋を見出し速度を上げる",
    "7381395868849311810": "最終コーナーで前の方で抜くと速度が\n後ろの方で抜くと加速力が上がる",
    "8961371806456758826": "中盤のコーナーで先団を走行中\n後ろに他ウマ娘を検知すると\nわずかに息を入れ、さらに速度を上げる",
    "12410767335950376473": "レース中間付近を好位置で走行中に\n詰め寄られると前方のウマ娘から\n持久力を吸い取る",
    "12801940097308914434": "最終コーナー以降に3回追い抜くと\n抱いた誇りを力に変えて\n最終直線で速度を上げ続ける",
    "15385091609844977618": "最終コーナー走行中に中団で競り合うと\n抜け出しやすくなる",
    "8170412585264284499": "最終直線を好位置で走行中\n前のウマ娘との距離が近いと\n抜け出しやすくなる",
    "7346061104355244773": "最終コーナーで先頭から離されていると\nその距離が遠いほど頑張り続けて\n速度を少しずつ上げる",
    "14300005774143945608": "レース後半に後方で詰め寄られると\nマシマシの幸運パワーが身体に実り\n速度が上がる",
    "15640628591134349011": "右回りコースが得意になる",
    "1733556100249808753": "右回りコースが少し得意になる",
    "665412858917846826": "右回りコースが少し苦手になる",
    "2348646054313484604": "左回りコースが得意になる",
    "12883022228291879798": "左回りコースが少し得意になる",
    "1347223574271645945": "左回りコースが少し苦手になる",
    "13526719642685377710": "東京レース場が得意になる",
    "8494010328335738932": "東京レース場が少し得意になる",
    "11153646257866652451": "東京レース場が少し苦手になる",
    "14691764021593496794": "中山レース場が得意になる",
    "7106738086405787296": "中山レース場が少し得意になる",
    "9031216517446723535": "中山レース場が少し苦手になる",
    "2673539012683469709": "阪神レース場が得意になる",
    "11530806279823210999": "阪神レース場が少し得意になる",
    "3487481018541929572": "阪神レース場が少し苦手になる",
    "1980019665487236667": "京都レース場が得意になる",
    "2896558136003987945": "京都レース場が少し得意になる",
    "9687679913813997074": "京都レース場が少し苦手になる",
    "10370208608104076895": "京都レース場が得意になり\nスタミナと賢さが上昇する",
    "9292361863087104013": "中京レース場が得意になる",
    "4545730153321910903": "中京レース場が少し得意になる",
    "6797249272299628516": "中京レース場が少し苦手になる",
    "14365433129867835874": "札幌レース場が得意になる",
    "6892081211992821880": "札幌レース場が少し得意になる",
    "5437521624991661015": "札幌レース場が少し苦手になる",
    "14213889141986461401": "函館レース場が得意になる",
    "696986316140242099": "函館レース場が少し得意になる",
    "3169076216750981808": "函館レース場が少し苦手になる",
    "3393429406511780026": "福島レース場が得意になる",
    "12737885215498875584": "福島レース場が少し得意になる",
    "5558935816997703855": "福島レース場が少し苦手になる",
    "2470867049040917045": "新潟レース場が得意になる",
    "10019830006323608207": "新潟レース場が少し得意になる",
    "7787611483455927212": "新潟レース場が少し苦手になる",
    "6034452250610346114": "小倉レース場が得意になる",
    "8172043840282757976": "小倉レース場が少し得意になる",
    "1228339635932638455": "小倉レース場が少し苦手になる",
    "12276120967680137815": "根幹距離（400mの倍数）が\n得意になる",
    "16174043965598360517": "根幹距離（400mの倍数）が\n少し得意になる",
    "4041422138213993582": "根幹距離（400mの倍数）が\n少し苦手になる",
    "3626474308210964678": "非根幹距離（400mの倍数以外）が\n得意になる",
    "1307460237600606524": "非根幹距離（400mの倍数以外）が\n少し得意になる",
    "1499775580866650555": "非根幹距離（400mの倍数以外）が\n少し苦手になる",
    "18328808865687600463": "「良」のバ場状態が得意になる",
    "11222856987051532461": "「良」のバ場状態が少し得意になる",
    "2403838925771196358": "「良」のバ場状態が少し苦手になる",
    "4231251066303350117": "「稍重」「重」「不良」のバ場状態が\n得意になる",
    "11575526896438521599": "「稍重」「重」「不良」のバ場状態が\n少し得意になる",
    "2417261703063352476": "「稍重」「重」「不良」のバ場状態が\n少し苦手になる",
    "6896522063531242577": "春のレースが得意になる",
    "2601664194681180987": "春のレースが少し得意になる",
    "1592071796761550824": "春のレースが少し苦手になる",
    "14209129446429685847": "春のレースが得意になり\nスピードとパワーが上昇する",
    "11923396212993403850": "夏のレースが得意になる",
    "1569877614059641936": "夏のレースが少し得意になる",
    "7681535250613319999": "夏のレースが少し苦手になる",
    "6594115741589504182": "秋のレースが得意になる",
    "15138803201300979116": "秋のレースが少し得意になる",
    "8953630323739493675": "秋のレースが少し苦手になる",
    "15958564857177837960": "秋のレースが得意になり\nスピードとパワーが上昇する",
    "6428751066631729173": "冬のレースが得意になる",
    "7626492455436455855": "冬のレースが少し得意になる",
    "8175754847572778892": "冬のレースが少し苦手になる",
    "10775080475619717608": "晴れの日のレースが得意になる",
    "18260497403512515554": "晴れの日のレースが少し得意になる",
    "17189774219888388529": "曇りの日のレースが得意になる",
    "107533966170313435": "曇りの日のレースが少し得意になる",
    "7478240835138638736": "雨の日のレースが得意になる",
    "17947032044287995386": "雨の日のレースが少し得意になる",
    "12263183667690108301": "雨の日のレースが少し苦手になる",
    "14261276298261446918": "雪の日のレースが得意になる",
    "17048149749337947516": "雪の日のレースが少し得意になる",
    "17387856302741042427": "枠番が1～3のレースが得意になる",
    "17455486568199119017": "枠番が1～3のレースが少し得意になる",
    "1635695573421048914": "枠番が1～3のレースが少し苦手になる",
    "18173229745980257107": "枠番が6～8のレースが得意になる",
    "13051241887095411697": "枠番が6～8のレースが少し得意になる",
    "4320965411886321834": "枠番が6～8のレースが少し苦手になる",
    "15480557379407364762": "自分と同じ作戦のウマ娘がいないと\n能力を発揮しやすい",
    "16214079043125732620": "自分と同じ作戦のウマ娘がいないと\n能力を少し発揮しやすい",
    "16469006005863788297": "自分と同じ作戦のウマ娘が6人以上だと\n能力を発揮しやすい",
    "1660619461833084695": "自分と同じ作戦のウマ娘が6人以上だと\n能力を少し発揮しやすい",
    "17723833053045283462": "自分と同じ作戦のウマ娘が6人以上だと\n能力を少し発揮しにくい",
    "17798425155183422126": "1番人気のウマ娘と作戦が同じだと\n能力を発揮しやすい",
    "5335394929844449472": "1番人気のウマ娘と作戦が同じだと\n能力を少し発揮しやすい",
    "17780784585538410384": "4番人気以下のレースで\n能力を発揮しやすい",
    "10603234862045573990": "4番人気以下のレースで\n能力を少し発揮しやすい",
    "6190498495721416885": "GⅠなどの大舞台のレースが\n少し苦手になる",
    "11689073974257462408": "1番人気になる事が少し苦手になる",
    "12089669929196646719": "コーナーが得意になり\n速度が上がる",
    "15866312893231426750": "コーナーが得意になり\n速度がわずかに上がる",
    "8173745504594253143": "コーナーが苦手になり\n速度が少し下がる",
    "13356278325009065527": "華麗なコーナーワークで\n加速力が上がる",
    "11590657523557222198": "華麗なコーナーワークで\n加速力がわずかに上がる",
    "18271692300253294219": "ぎこちないコーナーワークで\n加速力が少し下がる",
    "3891041375681684825": "無駄のないコーナリングで\n持久力が回復する",
    "6040572500537449904": "無駄のないコーナリングで\n持久力がわずかに回復する",
    "18323810506548258268": "無駄の多いコーナリングで\n持久力が少し減少する",
    "10584212128886546417": "直線で速度が上がる",
    "18123703811090379096": "直線で速度がわずかに上がる",
    "9761486381382127258": "直線で加速力が上がる",
    "9322805504221618451": "直線で加速力がわずかに上がる",
    "15144247165931817905": "直線で持久力が回復する",
    "6079278898094255304": "直線で持久力がわずかに回復する",
    "4169809816599560794": "上り坂で少し\n疲れてしまいがちになる",
    "13757175928814710264": "周りを囲まれると\n持久力が少し減少する",
    "12959515887130613298": "最終直線で最後方付近にいると\n少しあきらめてしまいがちになる",
    "10492046686891544178": "残り200m付近で先頭だと\n少し油断しがちになる",
    "8868629563614513242": "スタートが得意になり\n出遅れる時間が少なくなる",
    "15237745800660421927": "スタートが得意になり\n出遅れる時間がわずかに少なくなる",
    "7867837136002179586": "スタートが苦手になり\n出遅れる時間が少し増える",
    "16557752133935576573": "レース序盤に前が詰まった時に\n強い意志を保ち持久力が回復する",
    "12606906820664457391": "レース序盤に前が詰まった時に\n隠れて持久力がわずかに回復する",
    "7830461456954319141": "レース序盤にコース取りがうまくなる",
    "8597414561660108365": "レース序盤にコース取りが\n少しうまくなる",
    "2200658177975391969": "レース中盤に追い抜くと\n速度が上がる",
    "7288468775666807144": "レース中盤に追い抜くと\n速度がわずかに上がる",
    "13583520306567425302": "レース中盤に追い抜かれると\n持久力が回復する",
    "5899022519281678479": "レース中盤に追い抜かれると\n持久力がわずかに回復する",
    "5265508818389721397": "レース中盤に囲まれると\n持久力が回復する",
    "1024461217538427108": "レース中盤に囲まれると\n持久力がわずかに回復する",
    "8407060925579978300": "ラストスパートで前が塞がれた時の\n立ち回りがうまくなる",
    "12255641875364352569": "ラストスパートで前が塞がれた時の\n立ち回りがわずかにうまくなる",
    "17100074674916885877": "レース終盤にコース取りがうまくなる",
    "3649033935366868573": "レース終盤にコース取りが\n少しうまくなる",
    "3491791214599724462": "ラストスパートで速度が上がる",
    "4798257283082995343": "ラストスパートで速度がわずかに上がる",
    "7653376296998066704": "先頭で大きくリードし過ぎると\n少し疲れてしまいがちになる",
    "17956894986073695661": "レース序盤で\n前に行きやすくなる＜作戦・逃げ＞",
    "10399874006475750440": "レース序盤でわずかに\n前に行きやすくなる＜作戦・逃げ＞",
    "11699323196777577243": "レース中盤で\n前に行きやすくなる＜作戦・逃げ＞",
    "15354136390614713062": "レース中盤でわずかに\n前に行きやすくなる＜作戦・逃げ＞",
    "3721337161438021810": "最終コーナーで先頭を\nキープしやすくなる＜作戦・逃げ＞",
    "12943039951591420411": "最終コーナーで先頭をわずかに\nキープしやすくなる＜作戦・逃げ＞",
    "3205041088251027054": "レース序盤で疲れにくくなる\n＜作戦・先行＞",
    "9716486348521195263": "レース序盤でわずかに疲れにくくなる\n＜作戦・先行＞",
    "17234950867438298552": "レース中盤で疲れにくくなる\n＜作戦・先行＞",
    "6624777682095398729": "レース中盤でわずかに疲れにくくなる\n＜作戦・先行＞",
    "7978256406462801000": "最終コーナーで抜け出しやすくなる\n＜作戦・先行＞",
    "4238727824229316025": "最終コーナーでわずかに\n抜け出しやすくなる＜作戦・先行＞",
    "5582235454112995054": "レース中盤で速度が上がる\n＜作戦・差し＞",
    "14556821117017824231": "レース中盤で速度がわずかに上がる\n＜作戦・差し＞",
    "8042158133111527171": "レース終盤で加速力が上がる\n＜作戦・差し＞",
    "11473516978760677106": "レース終盤で加速力がわずかに上がる\n＜作戦・差し＞",
    "14256264186656937265": "最終コーナーで外から追い抜くと\n速度が上がる＜作戦・差し＞",
    "14772381297122017960": "最終コーナーで外から追い抜くと\n速度がわずかに上がる＜作戦・差し＞",
    "6908570849050861820": "レース中盤に脚を溜めて\n疲れにくくなる＜作戦・追込＞",
    "6068214118732845281": "レース中盤に脚を溜めて\nわずかに疲れにくくなる＜作戦・追込＞",
    "16979858075587197310": "レース終盤に追い込み態勢に入り\n位置を上げる＜作戦・追込＞",
    "7685679275150590043": "レース終盤に追い込み態勢に入り\n位置をわずかに上げる＜作戦・追込＞",
    "5158795761676989283": "ラストスパートの直線で\n加速力が上がる＜作戦・追込＞",
    "5918136212319155726": "ラストスパートの直線で\n加速力がわずかに上がる＜作戦・追込＞",
    "12739059166528013700": "直線で加速力が上がる\n＜短距離＞",
    "1787466274606305293": "直線で加速力がわずかに上がる\n＜短距離＞",
    "17049249832008333890": "レース中盤に後ろの方だと\nわずかに疲れにくくなる＜短距離＞",
    "18132310414375061318": "レース終盤に後ろの方だと\nスパートしやすくなる＜短距離＞",
    "10597819557478968435": "レース終盤に後ろの方だとわずかに\nスパートしやすくなる＜短距離＞",
    "4873865081529137208": "レース序盤に先頭だと\n差を広げやすくなる＜マイル＞",
    "13677094200884445477": "レース序盤に先頭だとわずかに\n差を広げやすくなる＜マイル＞",
    "17745836919550307598": "レース序盤に後ろの方だと\n疲れにくくなる＜マイル＞",
    "9322920627677050143": "レース序盤に後ろの方だと\nわずかに疲れにくくなる＜マイル＞",
    "8375263513840134638": "レース終盤に後ろの方だと\n追い抜く力が上がる＜マイル＞",
    "4240251481370099407": "レース終盤に後ろの方だと\n追い抜く力がわずかに上がる＜マイル＞",
    "18348404046114333690": "レース中盤に先頭だと\n疲れにくくなる＜中距離＞",
    "4574956722050888239": "レース中盤に先頭だと\nわずかに疲れにくくなる＜中距離＞",
    "1725432319690057973": "レース中盤に前の方だと\n好位置を取りやすくなる＜中距離＞",
    "17747348253470995256": "レース中盤に前の方だとわずかに\n好位置を取りやすくなる＜中距離＞",
    "1253304955596337555": "最終コーナーで追い抜かれると\n差し返しやすくなる＜中距離＞",
    "15811165571022407950": "最終コーナーで追い抜かれると\nわずかに差し返しやすくなる＜中距離＞",
    "4070548697010653176": "直線に入ると息を入れて疲れにくくなる\n＜長距離＞",
    "14238617941257429273": "直線に入ると息を入れてわずかに\n疲れにくくなる＜長距離＞",
    "1105261624162969563": "最終コーナーで内ラチ側にいると\n速度が上がる＜長距離＞",
    "10572719384497736870": "最終コーナーで内ラチ側にいると\n速度がわずかに上がる＜長距離＞",
    "3912649435442264964": "力を出し切った時に\n走る気力が復活する＜長距離＞",
    "8471350620115543265": "力を出し切った時に\n走る気力がわずかに復活する＜長距離＞",
    "13352439618988515249": "レース中盤に前の方にいると後ろの\n掛かったウマ娘がわずかに疲れる",
    "4892814122572894648": "レース中盤に前の方にいると後ろの\n掛かったウマ娘が疲れる",
    "7213041782593868661": "レース中盤に後ろの方にいると前の\n掛かったウマ娘がわずかに疲れる",
    "12199531491439201385": "作戦が逃げのウマ娘が掛かると\n落ち着くまで時間がかかる",
    "11602258372366652379": "作戦が先行のウマ娘が掛かると\n落ち着くまで時間がかかる",
    "15278010271015633850": "作戦が差しのウマ娘が掛かると\n落ち着くまで時間がかかる",
    "11949905218769356129": "作戦が追込のウマ娘が掛かると\n落ち着くまで時間がかかる",
    "9335611113050929908": "レース序盤に作戦・逃げのウマ娘を\nけん制してわずかに疲れやすくする",
    "3594608523177762860": "レース中盤に作戦・逃げのウマ娘を\n焦らせてわずかに疲れやすくする",
    "3751879397792319270": "レース終盤に作戦・逃げのウマ娘を\nためらわせて速度をわずかに下げる",
    "15091866743180261114": "レース序盤に作戦・先行のウマ娘を\nけん制してわずかに疲れやすくする",
    "11130859496185987962": "レース中盤に作戦・先行のウマ娘を\n焦らせてわずかに疲れやすくする",
    "16711470176203353748": "レース終盤に作戦・先行のウマ娘を\nためらわせて速度をわずかに下げる",
    "12175995603371148419": "レース序盤に作戦・差しのウマ娘を\nけん制してわずかに疲れやすくする",
    "1612506938547781859": "レース中盤に作戦・差しのウマ娘を\n焦らせてわずかに疲れやすくする",
    "13108254587937739221": "レース終盤に作戦・差しのウマ娘を\nためらわせて速度をわずかに下げる",
    "4897477088156944916": "レース序盤に作戦・追込のウマ娘を\nけん制してわずかに疲れやすくする",
    "14966515346016524852": "レース中盤に作戦・追込のウマ娘を\n焦らせてわずかに疲れやすくする",
    "17300108243123353958": "レース終盤に作戦・追込のウマ娘を\nためらわせて速度をわずかに下げる",
    "13100574210063628555": "大井レース場が得意になる",
    "655866532979185913": "大井レース場が少し得意になる",
    "16744003188832651426": "大井レース場が少し苦手になる",
    "4940055775744937735": "直線で速度が少し上がる＜短距離＞",
    "12856574143973784636": "直線で速度がわずかに上がる＜短距離＞",
    "2517869356995871": "コーナーで速度が少し上がる\n＜短距離＞",
    "4686714106891416812": "コーナーで速度がわずかに上がる\n＜短距離＞",
    "17735463135194400635": "レース中盤に大きく差をつけ先頭だと\nリードを保ちやすい＜短距離＞",
    "13033343760855661750": "レース中盤に大きく差をつけ先頭だと\nリードをわずかに保ちやすい＜短距離＞",
    "13127214104186500246": "レース中盤に前の方にいると\n抜かしやすくなる＜短距離＞",
    "14862967563985691535": "レース中盤に前の方にいると\nわずかに抜かしやすくなる＜短距離＞",
    "14867559026981370173": "レース中盤でゴールに向けて\n準備を整える＜短距離＞",
    "5088533324295899907": "レース中盤でゴールに向けて\n準備を少し整える＜短距離＞",
    "7613190530568642730": "レース序盤に前の方にいると\n後方のウマ娘が萎縮する＜短距離＞",
    "53922912999724480": "レース序盤に前の方にいると\n後方のウマ娘が少し萎縮する＜短距離＞",
    "821468775837433761": "レース序盤に後ろの方にいると\n前方のウマ娘が焦る＜短距離＞",
    "10446357872189262532": "レース序盤に後ろの方にいると前方の\nウマ娘がわずかに焦る＜短距離＞",
    "16625894655677521468": "直線で速度が少し上がる＜マイル＞",
    "16481390550737875767": "直線で速度がわずかに上がる＜マイル＞",
    "74568106389940516": "コーナーで速度が少し上がる\n＜マイル＞",
    "11455875801921440455": "コーナーで速度がわずかに上がる\n＜マイル＞",
    "3978944568376408341": "レース中盤に前の方にいると\n抜かしやすくなる＜マイル＞",
    "6964925284750851572": "レース中盤に前の方にいると\nわずかに抜かしやすくなる＜マイル＞",
    "11515567377762101845": "レース中盤に追い抜くと\n加速力が上がる＜マイル＞",
    "1399876179711449620": "レース中盤に追い抜くと\n加速力がわずかに上がる＜マイル＞",
    "11992136970814710796": "追い抜きが成功しやすくなる\n＜マイル＞",
    "8593625480329464329": "追い抜きがわずかに成功しやすくなる\n＜マイル＞",
    "8136554128332958295": "レース中盤に先頭にいると\n後ろの速度を少し奪う＜マイル＞",
    "426109164852263600": "レース中盤に先頭にいると\n後ろの速度をわずかに奪う＜マイル＞",
    "3570998251919479562": "レース序盤に後ろにいると\n前の動きを鈍くする＜マイル＞",
    "7190091892197812771": "レース序盤に後ろにいると\n前の動きをわずかに鈍くする＜マイル＞",
    "1964236402075802504": "直線で速度が少し上がる＜中距離＞",
    "227763433495518667": "直線で速度がわずかに上がる＜中距離＞",
    "13776347804669423070": "直線で速度が上がる＜中距離＞",
    "13622379300373962608": "コーナーで速度が少し上がる\n＜中距離＞",
    "6797571498748183707": "コーナーで速度がわずかに上がる\n＜中距離＞",
    "5785571808037871449": "レース序盤に観察力が高まり\n視野を広く持てる＜中距離＞",
    "694397232828050291": "レース序盤に観察力が高まり\n視野を少し広く持てる＜中距離＞",
    "16950273069704038575": "レース中盤に後ろの方にいると\n囲まれにくくなる＜中距離＞",
    "2038669877163576081": "レース中盤に後ろの方にいると\n少し囲まれにくくなる＜中距離＞",
    "7618496921743884640": "左右に動いても疲れにくくなる\n＜中距離＞",
    "7304938926425328893": "左右に動いてもわずかに疲れにくくなる\n＜中距離＞",
    "15403165788941880605": "レース終盤に後ろの方にいると\n前の速度を下げる＜中距離＞",
    "16874016947644611696": "レース終盤に後ろの方にいると\n前の速度をわずかに下げる＜中距離＞",
    "18336956461838430399": "レース中盤にすぐ前のウマ娘を\n戸惑わせる＜中距離＞",
    "15261291922704922378": "レース中盤にすぐ前のウマ娘を\nわずかに戸惑わせる＜中距離＞",
    "3803574657534480039": "直線で速度が少し上がる＜長距離＞",
    "5341525195525980576": "直線で速度がわずかに上がる＜長距離＞",
    "6380541096118989679": "コーナーで速度が少し上がる\n＜長距離＞",
    "14438128846892329776": "コーナーで速度がわずかに上がる\n＜長距離＞",
    "9763038691602891451": "レース中盤に大きく差をつけ先頭だと\nリードを保ちやすい＜長距離＞",
    "13362138056724537666": "レース中盤に大きく差をつけ先頭だと\nリードをわずかに保ちやすい＜長距離＞",
    "10129259572599707911": "追い抜く気持ちが湧き\n疲れにくくなる＜長距離＞",
    "13942610062481189866": "追い抜く気持ちが湧き\nわずかに疲れにくくなる＜長距離＞",
    "6717717485741974175": "レース終盤で追い抜くと\n速度が上がる＜長距離＞",
    "13066245035334632066": "レース終盤で追い抜くと\n速度がわずかに上がる＜長距離＞",
    "9288179427756185997": "レース中盤で後ろの方にいると\n前方の持久力をわずかに奪う＜長距離＞",
    "21410642125721141": "レース中盤で後ろの方にいると\n前方の持久力をちょっと奪う＜長距離＞",
    "14955273564223312552": "レース終盤で前方のウマ娘の\n視野が狭くなる＜長距離＞",
    "9987273435507091258": "レース終盤で前方のウマ娘の\n視野が少し狭くなる＜長距離＞",
    "11835001687887256804": "直線で速度が少し上がる\n＜作戦・逃げ＞",
    "15238967100019482695": "直線で速度がわずかに上がる\n＜作戦・逃げ＞",
    "9474268900896962530": "コーナーで速度が少し上がる\n＜作戦・逃げ＞",
    "11715051684133725073": "コーナーで速度がわずかに上がる\n＜作戦・逃げ＞",
    "18039834660658751811": "レース序盤に囲まれにくくなる\n＜作戦・逃げ＞",
    "16684990842942039069": "レース序盤に少し囲まれにくくなる\n＜作戦・逃げ＞",
    "16335813861403794249": "レース序盤にわずかに\n追い抜かれにくくなる＜作戦・逃げ＞",
    "13803165331254601547": "上り坂で疲れにくくなる\n＜作戦・逃げ＞",
    "5763419637002575870": "上り坂でわずかに疲れにくくなる\n＜作戦・逃げ＞",
    "16162662382262417606": "レース中盤に後ろにいると\n加速力が上がる＜作戦・逃げ＞",
    "5519199642518843723": "レース中盤に後ろにいると\n加速力がわずかに上がる＜作戦・逃げ＞",
    "7678475402545717515": "レース序盤に逃げに失敗した時\n前がわずかに動揺する＜作戦・逃げ＞",
    "8359588029052621498": "直線で速度が少し上がる\n＜作戦・先行＞",
    "1052139401602501777": "直線で速度がわずかに上がる\n＜作戦・先行＞",
    "13934109310160753744": "コーナーで速度が少し上がる\n＜作戦・先行＞",
    "587094336603202179": "コーナーで速度がわずかに上がる\n＜作戦・先行＞",
    "10724990746074484540": "コース取りが少しスムーズになる\n＜作戦・先行＞",
    "11505194299238962291": "コース取りがわずかにスムーズになる\n＜作戦・先行＞",
    "9123679029503021614": "下り坂が少し得意になる\n＜作戦・先行＞",
    "6811917279366179693": "下り坂がわずかに得意になる\n＜作戦・先行＞",
    "15064512004167850555": "レース中盤に持久力が回復する\n＜作戦・先行＞",
    "9201219710504432362": "レース中盤に持久力がわずかに回復する\n＜作戦・先行＞",
    "11474514194903885834": "レース中盤に後ろの方にいると\n加速力が少し上がる＜作戦・先行＞",
    "1287129299366015305": "レース中盤に後ろの方にいると\n加速力がわずかに上がる＜作戦・先行＞",
    "413680487982888968": "レース終盤に前の方にいると後方の\n視野が少し狭くなる＜作戦・先行＞",
    "467078406465035867": "レース終盤に前の方にいると後方の\n視野がわずかに狭くなる＜作戦・先行＞",
    "5071199225822374335": "直線で速度が少し上がる\n＜作戦・差し＞",
    "4251820785073932300": "直線で速度がわずかに上がる\n＜作戦・差し＞",
    "9792040060032655157": "コーナーで速度が少し上がる\n＜作戦・差し＞",
    "17796008544241449494": "コーナーで速度がわずかに上がる\n＜作戦・差し＞",
    "13743646730863959039": "追い抜きが少し成功しやすくなる\n＜作戦・差し＞",
    "10718798161351066424": "追い抜きがわずかに成功しやすくなる\n＜作戦・差し＞",
    "9018305512322520151": "上り坂で速度が上がる\n＜作戦・差し＞",
    "863863552932131038": "上り坂で速度がわずかに上がる\n＜作戦・差し＞",
    "2446968085453191300": "レース終盤に持久力が回復する\n＜作戦・差し＞",
    "16167830229610430877": "レース終盤に持久力がわずかに回復する\n＜作戦・差し＞",
    "10774484686340233006": "レース中盤に観察力が高まり\n視野を広く持てる＜作戦・差し＞",
    "9561826982421517959": "レース中盤に観察力が高まり視野を\nわずかに広く持てる＜作戦・差し＞",
    "11162897632157445186": "レース終盤に他のウマ娘が\n動揺する＜作戦・差し＞",
    "14404948792131723587": "レース終盤に他のウマ娘が\nわずかに動揺する＜作戦・差し＞",
    "10403027842058101444": "直線で速度が少し上がる\n＜作戦・追込＞",
    "946457291805030399": "直線で速度がわずかに上がる\n＜作戦・追込＞",
    "9195338097872306122": "コーナーで速度が少し上がる\n＜作戦・追込＞",
    "13689378986433539457": "コーナーで速度がわずかに上がる\n＜作戦・追込＞",
    "6499176381853730872": "左右に移動すると状況を把握して\n視野が少し広くなる＜作戦・追込＞",
    "8592457855789610555": "左右に移動すると状況を把握して\n視野がわずかに広くなる＜作戦・追込＞",
    "17556441601268825414": "下り坂で疲れにくくなる\n＜作戦・追込＞",
    "963294862692259843": "下り坂でわずかに疲れにくくなる\n＜作戦・追込＞",
    "7334570660776867095": "前が詰まった時に落ち着いて\n態勢を立て直す＜作戦・追込＞",
    "18067218862980197254": "前が詰まった時に落ち着いて\n態勢をわずかに立て直す＜作戦・追込＞",
    "3873132623984582592": "レース終盤に後ろの方にいると\n視野が広くなる＜作戦・追込＞",
    "8587238492195444613": "レース終盤に後ろの方にいると\n視野がわずかに広くなる＜作戦・追込＞",
    "5360159940543543086": "レース終盤に目を付けたウマ娘の\n緊張感が増す＜作戦・追込＞",
    "14096912464399261231": "レース終盤に目を付けたウマ娘の\n緊張感がわずかに増す＜作戦・追込＞",
    "16887436386515290477": "良い位置につきやすくなる\n＜作戦・逃げ＞",
    "12895582138593291891": "良い位置に少しつきやすくなる\n＜作戦・逃げ＞",
    "13649310861925011991": "良い位置につきやすくなる\n＜作戦・先行＞",
    "12749738312921784949": "良い位置に少しつきやすくなる\n＜作戦・先行＞",
    "9439786142144225754": "良い位置につきやすくなる\n＜作戦・差し＞",
    "3882171949329468240": "良い位置に少しつきやすくなる\n＜作戦・差し＞",
    "5402027066063515005": "良い位置につきやすくなる\n＜作戦・追込＞",
    "17363281892867210411": "良い位置に少しつきやすくなる\n＜作戦・追込＞",
    "13235070014114168436": "枠番が7の時に\n良いことが起きる場合がある",
    "12017242637888645978": "枠番が7の時に少し\n良いことが起きる場合がある",
    "13586506204529190006": "残り距離が777mの時に\nわずかに元気が出る",
    "6047539990450696306": "上り坂がわずかに上手くなる",
    "14415216831524663057": "近くにウマ娘がたくさんいると\n速度がわずかに上がる",
    "2464027504565023480": "近くにウマ娘がたくさんいると\n速度が上がる",
    "10491668839583217366": "レース序盤にスキルを多く発動すると\n加速力がわずかに上がる",
    "10922684634165104079": "レース中盤にスキルを多く発動すると\n速度がわずかに上がる",
    "3520429034799607918": "レース中盤にスキルを多く発動すると\n速度が上がる",
    "11374786578062263277": "レース終盤にスキルを多く発動すると\n持久力がわずかに回復する",
    "2613613710355032036": "シンパシーの心を持つウマ娘が多い\nレースだと少し能力が上がる",
    "10464205773999676282": "自分だけが一匹狼の心を持つレースで\n少し能力が上がる",
    "10854851064261003078": "前のウマ娘のすぐ後ろに付けると\n風の抵抗をわずかに受けにくくなる",
    "9466657337285216250": "すぐ後ろにウマ娘が長くいると\n速度がわずかに上がる",
    "17205442789382067358": "レース中盤に競り合うと\n速度が上がる＜ダート＞",
    "13071794140879242071": "レース中盤に競り合うと\n速度がわずかに上がる＜ダート＞",
    "11811374181391346037": "レース終盤に前を目指す\n体勢をとる＜ダート＞",
    "4174729645434358311": "レース終盤に少し前を目指す\n体勢をとる＜ダート＞",
    "436036304677565399": "レース中盤が迫ったとき後方にいると\n持久力を回復する＜作戦・差し＞",
    "646743619257024348": "レース中盤が迫ったとき後方にいると\n持久力をわずかに回復する\n＜作戦・差し＞",
    "14564519096417232335": "ラストスパートの直線で好位置にいると\n速度が上がる＜中距離＞",
    "14364471777730219610": "ラストスパートの直線で好位置にいると\n速度がわずかに上がる＜中距離＞",
    "1455682356533715030": "レース終盤に前方にいると\n加速力がわずかに上がる＜作戦・先行＞",
    "10131131634283179140": "レース中盤に後方にいると\n持久力がわずかに回復する＜ダート＞",
    "3403208795151596355": "レース終盤が迫ったとき前方にいると\n速度が上がる＜長距離＞",
    "1599005084593947438": "レース終盤が迫ったとき前方にいると\n速度がわずかに上がる＜長距離＞",
    "13399983135903323013": "レース中盤に後方にいると\nしばらくの間速度が少し上がる\n＜作戦・追込＞",
    "3686583062419791142": "レース中盤に後方にいると\nしばらくの間速度がちょっと上がる\n＜作戦・追込＞",
    "9369807998163366773": "レース後半に速度がすごく上がるが\nすごく疲れてしまうことがある",
    "12557472769947362813": "レース後半に速度が少し上がるが\nすごく疲れてしまうことがある",
    "5518523660616481491": "レース終盤が迫ったとき前方にいると\n速度が上がる＜短距離＞",
    "12714842050306937810": "レース終盤が迫ったとき前方にいると\n速度がわずかに上がる＜短距離＞",
    "10625047885403353870": "レース中盤にアオハル魂が燃え\nレース中のチームメンバーの\nスピード合計が高いほど速度が上がる",
    "11574075367769143135": "レース中盤にアオハル魂が燃え\nレース中のチームメンバーのスピード\n合計が高いほど速度がわずかに上がる",
    "7902140724116501189": "レース中盤にアオハル魂が燃え\nレース中のチームメンバーのスタミナ\n合計が高いほど持久力が回復する",
    "12748326828055689004": "レース中盤にアオハル魂が燃えレース\n中のチームメンバーのスタミナ合計が\n高いほど持久力がわずかに回復する",
    "16715174996983647249": "レース終盤にアオハル魂が燃え\nレース中のチームメンバーの\nパワー合計が高いほど加速力が上がる",
    "2326148559071938344": "レース終盤にアオハル魂が燃え\nレース中のチームメンバーのパワー\n合計が高いほど加速力がわずかに上がる",
    "8945164392445308875": "レース終盤にアオハル魂が燃え\nレース中のチームメンバーの根性合計が\n高いほど脚に力強さが宿る",
    "3716577668675154146": "レース終盤にアオハル魂が燃え\nレース中のチームメンバーの根性合計が\n高いほど脚にちょっと力強さが宿る",
    "13433555800231860845": "レース序盤にアオハル魂が燃え\nレース中のチームメンバーの賢さ合計が\n高いほど先を見据えたコース取りを行う",
    "17127468523661517392": "レース序盤にアオハル魂が燃えレース中\nのチームメンバーの賢さ合計が高いほど\nわずかに先を見据えたコース取りを行う",
    "15558008947677545455": "レースへの渇望により\n能力が少し発揮しやすくなる",
    "3225829994728931694": "かつての走りとは違うがあの頃と\n変わらない想いが能力をすごく上げる",
    "12704737143486098653": "見たい景色を必死に追いかけ\n能力が少し発揮しやすくなる",
    "882335996584889333": "トレーナーの恐れが伝播し\n能力が少し発揮しにくくなる",
    "15943947009147552967": "トレーナーの恐れがより鮮明になり\nレース後半のコーナーで\n速度がすごく下がる",
    "7454913795395778794": "みんなの想いと共に\nゴールを走り抜ける気持ちを強く持つと\n最終直線で速度を上げる",
    "11738751412847260783": "次のステージを見せてくれる\n期待を伝えてサイレンススズカの\n能力を少し発揮しやすくさせる",
    "12047998701917502063": "気持ちよく走れるおまじないをして\nサイレンススズカの能力を\n少し発揮しやすくさせる",
    "5481445031280410291": "自分だけの走りを見つけた\n親友への激励がサイレンススズカの\n能力を少し発揮しやすくさせる",
    "8847031561685332537": "レース後半のコーナーで思いっきりの\n応援が届くとサイレンススズカの\n持久力が回復する",
    "6839298977124537423": "レース終盤に前の方で相手を抜くと\n速度がわずかに上がる",
    "16128613205494451330": "最終直線で差を付けて先頭にいると\n速度をわずかに上げる",
    "12784754965246841612": "最終直線で前と差が詰まると\n速度が少し上がる",
    "7975015989006650672": "最終コーナー以降で前の方にいると\n加速力がわずかに上がる",
    "8756968913309379908": "最終直線で前の方で少し抜け出ていると\n速度が少し上がる",
    "3802336073815521260": "残り200m地点で前の方にいると\n少し抜け出しやすくなる",
    "13985043810179028176": "レース中間からロングスパートをかけて\n速度がちょっとずつ上がる",
    "14148614344825563996": "残り200mを切って前の方にいると\n速度がわずかに上がる",
    "13326406864640264944": "レース後半で1番を\nキープし続ける力をちょっと発揮する",
    "13043030489719739554": "最終コーナーで好位置にいると\n加速力がわずかに上がる",
    "14038982613924156973": "最終直線で後ろの方から追い抜くと\n速度がわずかに上がる",
    "16887647507611086166": "最終直線で後ろの方から外を回って\n追い抜く時、速度をわずかに上げる",
    "12922385158722083171": "最終コーナーで前の方にいると\n速度がわずかに上がる",
    "14193931173962827062": "最終直線で余力を持って前にいると\nちょっと優位を保ちやすくなる",
    "3599708533967595204": "最終コーナーで前の方で競り合うと\n速度がわずかに上がる",
    "15577027467280727058": "最終コーナー以降で外から追い抜くと\n速度をわずかに上げる",
    "14944569720437816034": "レース終盤に3回追い抜くと\n最終直線で速度が少し上がる",
    "5046030368807012283": "最終コーナーで後ろから追い抜くと\n速度がわずかに上がる",
    "4372582878473871564": "レース終盤に2回追い抜くと\n速度をわずかに上げる",
    "7108253869448089525": "レース終盤のコーナーで先頭にいると\n加速力をわずかに上げる",
    "1387643260336886119": "レース後半の直線で好位置にいる\nまたは中団から前を狙うと\nわずかに駆けて行く",
    "12746260867044041848": "レース後半に好位置で競り合うと\n速度をわずかに上げる",
    "17681718599512061889": "最終コーナーで前の方で追い抜くと\n速度をわずかに上げる",
    "6698355842401416486": "最終コーナーで前の方で競り合うと\n直線でちょっと抜け出しやすくなる",
    "5661440406255684527": "レース後半に中団から\n速度をちょっとずつ上げ前方のウマ娘を\nほんのちょっと委縮させる",
    "11357685094648262683": "最終直線までみずから崩れることなく\n前の方にいるとわずかに速度が上がる",
    "6331998496118222418": "レース終盤のコーナーで前の位置に\nつこうとして加速力がわずかに上がる",
    "10667998431373874348": "レース中間に好位置で少し疲れてくると\nちょっと前へ踏み込む",
    "12539574349771056871": "最終直線で抜け出した時に\n速度がわずかに上がる",
    "8317156029980109174": "レース後半のコーナーで控えていると\n持久力がわずかに回復する",
    "16911077561013550106": "最終直線で先頭から離されていると\n速度がわずかに上がる\n最後方付近にいる場合は少し上がる",
    "13384123156353686839": "最終直線で競り合いに負けない\n気持ちが湧けば、速度がわずかに上がる",
    "11405851116579920183": "最終直線まで冷静に自身の計画通り\n走行出来れば、先頭目がけて\n速度をわずかに上げる",
    "8174874074917933069": "レース中間付近で好位置にいる時に\n追い抜くとちょっと進出を開始する",
    "945198172005546881": "最終直線を走行中に中団で競り合うと\n速度をわずかに上げる",
    "16495477333873069470": "レース後半に中団から仕掛け始める時に\n加速力をちょっとずつ上げる",
    "13358540934838525718": "レース後半に前の方で競り合うと\n速度がわずかに上がる",
    "16126091038521725831": "レース中盤で好位置にいる時に\n持久力がわずかに回復する",
    "10152889630990957683": "レース中盤の直線で先頭を奪われそうに\nなると譲らない想いがちょっと力になる",
    "7288800224039380607": "最終直線を走行中に好位置で\n追い抜くまたは詰め寄られると\nわずかに速度を上げる",
    "7421433042651021271": "最終コーナーで集団の後方の位置から\n前へ出る時、速度がわずかに上がる",
    "2960244789877242293": "最終コーナーで後ろの方にいると近くの\nウマ娘を見て持久力をわずかに回復する",
    "12400136699224505612": "レース終盤に前方が詰まると\nお告げ次第で道をわずかに切り開く",
    "11699407712955706225": "レース終盤のコーナーで\n中団以降のポジションから追い抜くと\nちょっと前を目指す",
    "2729196886924262723": "落ち着いたまま、中盤の仕掛けどころの\nまたは終盤の勝負どころのコーナーを\n中団で進むとわずかに加速力が上がる",
    "604092301339675645": "レース終盤で3番手の時に負けそうに\nなると速度がわずかに上がる",
    "1607236122244455095": "レースを冷静に運ぶことができると残り\n200mで実力発揮、速度が少し上がる",
    "9698296906623651619": "残り300mを切って好位置にいるとき\n前のウマ娘との距離が近いと\n速度がわずかに上がる",
    "1149643935349391098": "最終直線で後ろのウマ娘と距離が近いと\n持久力をわずかに使い\n少しの間速度が少し上がる",
    "14464873065042050667": "中盤で2回スキルを使うと\n持久力がわずかに回復する",
    "1043523029706501717": "最終直線で前の方で追いすがっていると\n速度がわずかに上がる",
    "1689075867000742457": "スキルで持久力を回復すると\nレース後半で前のほうにいる時に\nわずかに速度を上げる",
    "1969137395118780984": "スキルで持久力を3回以上回復すると\nレース後半で勝利に向かい\nちょっと呼吸を整えて踏み込んでいく",
    "18204586334547132970": "中盤に後ろの方で順位を下げた時に\n持久力をわずかに回復する",
    "7389886077742594842": "最終コーナー以降に前めで力が尽きかけ\n詰め寄られると速度がわずかに上がる",
    "15072683916933748575": "最終コーナーで中団から前を狙う時\n加速力をわずかに上げる",
    "9723309331715979436": "残り400m地点で先団だと少しの間\n速度をわずかに上げる、それまでに7回\nスキルを使っている場合は少し上げる",
    "13676588293763121241": "最終コーナー以降に先団で\n詰め寄られるとわずかに速度を上げる",
    "5520315049954509205": "レース中盤で前の方から\n仕掛け始める時に速度がわずかに上がる",
    "4168122102094086997": "スタート後からレース後半まで\n好位置を維持し続けると\nレース中盤に速度をわずかに上げる",
    "737167999136160303": "最終コーナーで前の方で抜くと速度が後\nろの方で抜くと加速力がわずかに上がる",
    "7340845311681746309": "中盤のコーナーで先団を走行中\n後ろに他ウマ娘がいるとほんのわずかに\n息を入れ、さらに速度をわずかに上げる",
    "204762914610432596": "レース中間付近を好位置で走行中に\n詰め寄られると前方のウマ娘から\n持久力をわずかに吸い取る",
    "9218648657816380978": "最終コーナー以降に3回追い抜くと\n最終直線で速度をわずかに上げ続ける",
    "5701250223897205799": "最終コーナー走行中に中団で競り合うと\nちょっと抜け出しやすくなる",
    "11760386296338013494": "最終直線を好位置で走行中\n前のウマ娘との距離が近いと\nちょっと抜け出しやすくなる",
    "12955320747629275886": "最終コーナーで先頭から離されていると\nその距離が遠いほど頑張り続けて\n速度をちょっとずつ上げる",
    "1522752199718101615": "レース後半に後方で詰め寄られると\n幸運パワーが身体に実り\n速度がわずかに上がる",
    "18095170245529979374": "レーシングカーニバルで獲得するカーニ\nバルptにボーナスが付く（＋{0}％）\nこのスキルはイベント終了時に消滅する"
}